{
    "faqs": [
        {
            "question": "제2차 세계 대전은 언제 시작되었나요?",
            "answer": "제2차 세계 대전은 1939년 9월 1일, 나치 독일이 폴란드를 침공하면서 시작되었습니다."
        },
        {
            "question": "제2차 세계 대전의 주된 양대 진영은 무엇인가요?",
            "answer": "연합국과 추축국이 주요 양대 진영이었습니다. 연합국에는 미국, 영국, 소련, 프랑스, 중국이 포함되었으며, 추축국에는 나치 독일, 이탈리아 왕국, 일본 제국이 포함되었습니다."
        },
        {
            "question": "제2차 세계 대전은 언제 종전되었나요?",
            "answer": "제2차 세계 대전은 1945년 9월 2일에 종전되었습니다."
        },
        {
            "question": "제2차 세계 대전의 주요 원인은 무엇이었나요?",
            "answer": "주요 원인은 독일의 베르사유 조약 파기와 군사 강화, 일본의 제국주의 정책, 그리고 세계 경제 대공황 등이 있습니다."
        },
        {
            "question": "제2차 세계 대전의 주요 전선은 어떤 것들이었나요?",
            "answer": "주요 전선으로는 유럽 전선, 태평양 전선, 북아프리카 전역, 동부 전선(독소전쟁) 등이 있습니다."
        },
        {
            "question": "제2차 세계 대전에서 나치 독일의 주요 지도자는 누구였나요?",
            "answer": "나치 독일의 주요 지도자는 아돌프 히틀러였습니다."
        },
        {
            "question": "제2차 세계 대전 중 연합국의 주요 사망자 수는 얼마나 되나요?",
            "answer": "연합국의 군인 사망자 수는 약 16,000,000명 이상이었습니다."
        },
        {
            "question": "제2차 세계 대전에 참전한 추축국의 주요 국가는 어디였나요?",
            "answer": "나치 독일, 이탈리아 왕국, 일본 제국이 주요 추축국이었습니다."
        },
        {
            "question": "제2차 세계 대전 중 가장 큰 전투는 어디서 벌어졌나요?",
            "answer": "스탈린그라드 전투가 제2차 세계 대전 중 가장 큰 전투 중 하나로 꼽힙니다."
        },
        {
            "question": "제2차 세계 대전 이후 세계의 정치적 질서에 어떤 변화가 일어났나요?",
            "answer": "제2차 세계 대전 이후 미국과 소련이 주요 초강대국으로 떠오르며 냉전 체제가 시작되었습니다."
        },
        {
            "question": "제2차 세계 대전 종전 후 일본과 독일은 어떻게 변화했나요?",
            "answer": "일본은 민주주의 체제로 전환하며 천황제는 유지되었지만, 독일은 동서로 분단되었습니다."
        },
        {
            "question": "제2차 세계 대전의 경제적 영향은 무엇이었나요?",
            "answer": "전쟁으로 인해 유럽의 많은 국가들이 경제적으로 황폐해졌으며, 미국은 경제적 초강대국으로 떠올랐습니다."
        },
        {
            "question": "제2차 세계 대전의 인구 피해는 어느 정도였나요?",
            "answer": "전쟁으로 인해 약 50,000,000에서 80,000,000명의 인명이 희생되었습니다."
        },
        {
            "question": "제2차 세계 대전을 통해 어떤 국제 기구가 창설되었나요?",
            "answer": "제2차 세계 대전 이후 유엔(UN)이 창설되었습니다."
        },
        {
            "question": "제2차 세계 대전 중 가장 많은 사상자가 발생한 전투는 무엇인가요?",
            "answer": "많은 학자들이 스탈린그라드 전투를 가장 많은 사상자가 발생한 전투로 보고 있습니다."
        },
        {
            "question": "'불공정한 평화 조약'이란 무엇을 의미하나요?",
            "answer": "'불공정한 평화 조약'은 베르사유 조약을 가리키며, 독일에게 가혹한 조건을 부과했던 조약으로 여겨집니다."
        },
        {
            "question": "제2차 세계 대전의 결과로 인한 핵무기의 중요성은 어떻게 되었나요?",
            "answer": "핵무기는 제2차 세계 대전 이후 국제 정치와 군사 전략에서 핵심적인 역할을 하게 되었습니다."
        },
        {
            "question": "제2차 세계 대전 중 일본 내에서 발생한 주요 사건은 무엇이었나요?",
            "answer": "일본의 진주만 공습과, 히로시마·나가사키 원자폭탄 투하가 주요 사건이었습니다."
        },
        {
            "question": "제2차 세계 대전에서 이탈리아의 최종 결과는 어떻게 되었나요?",
            "answer": "이탈리아는 연합국으로 전환한 후 전후에 상실한 영토가 적고, 이후 민주 공화정으로 전환했습니다."
        },
        {
            "question": "제2차 세계 대전은 어떤 사조나 패러다임의 변화를 가져왔나요?",
            "answer": "제2차 세계 대전은 전체주의와 제국주의의 쇠퇴, 그리고 냉전 체제의 시작, 민주주의와 탈식민지화의 촉진을 가져왔습니다."
        }
    ]
}